brainrender_napari/__init__.py
brainrender_napari/brainrender_manager_widget.py
brainrender_napari/brainrender_viewer_widget.py
brainrender_napari/napari.yaml
brainrender_napari/napari_atlas_representation.py
brainrender_napari/data_models/__init__.py
brainrender_napari/data_models/atlas_table_model.py
brainrender_napari/data_models/structure_tree_model.py
brainrender_napari/utils/__init__.py
brainrender_napari/utils/formatting.py
brainrender_napari/utils/load_user_data.py
brainrender_napari/widgets/__init__.py
brainrender_napari/widgets/atlas_manager_dialog.py
brainrender_napari/widgets/atlas_manager_filter.py
brainrender_napari/widgets/atlas_manager_view.py
brainrender_napari/widgets/atlas_progress_bar.py
brainrender_napari/widgets/atlas_viewer_view.py
brainrender_napari/widgets/structure_view.py
brainrender_napari-0.1.4.dist-info/licenses/LICENSE
brainrender_napari-0.1.4.dist-info/METADATA
brainrender_napari-0.1.4.dist-info/WHEEL
brainrender_napari-0.1.4.dist-info/entry_points.txt
brainrender_napari-0.1.4.dist-info/top_level.txt
brainrender_napari-0.1.4.dist-info/RECORD
