Metadata-Version: 2.4
Name: brainrender-napari
Version: 0.1.4
Summary: A napari plugin to render BrainGlobe atlases and associated data as layers.
Author-email: Alessandro Felder <a.felder@ucl.ac.uk>
License: BSD-3-Clause
Project-URL: Homepage, https://github.com/brainglobe/brainrender-napari
Project-URL: Bug Tracker, https://github.com/brainglobe/brainrender-napari/issues
Project-URL: Documentation, https://brainglobe.github.io/brainrender-napari
Project-URL: Source Code, https://github.com/brainglobe/brainrender-napari
Project-URL: User Support, https://github.com/brainglobe/brainrender-napari/issues
Classifier: Development Status :: 2 - Pre-Alpha
Classifier: Framework :: napari
Classifier: Intended Audience :: Developers
Classifier: Programming Language :: Python
Classifier: Programming Language :: Python :: 3
Classifier: Programming Language :: Python :: 3.11
Classifier: Programming Language :: Python :: 3.12
Classifier: Programming Language :: Python :: 3.13
Classifier: Operating System :: OS Independent
Classifier: License :: OSI Approved :: BSD License
Classifier: Topic :: Scientific/Engineering :: Image Processing
Requires-Python: >=3.11.0
License-File: LICENSE
Requires-Dist: brainglobe-atlasapi>=2.2.0
Requires-Dist: brainglobe-utils>=0.4.3
Requires-Dist: meshio
Requires-Dist: napari>=0.6.1
Requires-Dist: numpy
Requires-Dist: qtpy
Provides-Extra: dev
Requires-Dist: pytest; extra == "dev"
Requires-Dist: pytest-cov; extra == "dev"
Requires-Dist: pytest-mock; extra == "dev"
Requires-Dist: pytest-qt; extra == "dev"
Requires-Dist: coverage; extra == "dev"
Requires-Dist: tox; extra == "dev"
Requires-Dist: black; extra == "dev"
Requires-Dist: mypy; extra == "dev"
Requires-Dist: pre-commit; extra == "dev"
Requires-Dist: ruff; extra == "dev"
Requires-Dist: setuptools_scm; extra == "dev"
Requires-Dist: pyqt5; extra == "dev"
Dynamic: license-file
